mahutils/__init__.py
mahutils/tools.py
mahutils-1.2.dist-info/METADATA
mahutils-1.2.dist-info/WHEEL
mahutils-1.2.dist-info/top_level.txt
mahutils-1.2.dist-info/RECORD
