Metadata-Version: 2.4
Name: mahutils
Version: 1.2
Summary: myutils : Your complete math solution in Python.
Author-email: Mahmoud <mahmood.alh513@gmail.com>
License: MIT
Requires-Python: >=3.7
